algorithms/__init__.py
algorithms/a_star.py
algorithms/best_first.py
algorithms/branch_and_bound.py
algorithms/breadth_first.py
algorithms/depth_first.py
algorithms/hill_climbing.py
algorithms/iterative_deepening.py
algorithms/uniform_cost.py
data_structures/__init__.py
data_structures/priority_queue.py
data_structures/queue.py
data_structures/stack.py
interfaces/__init__.py
interfaces/state_space_problem.py
omnisearch/__init__.py
omnisearch/algorithms/__init__.py
omnisearch/algorithms/a_star.py
omnisearch/algorithms/best_first.py
omnisearch/algorithms/branch_and_bound.py
omnisearch/algorithms/breadth_first.py
omnisearch/algorithms/depth_first.py
omnisearch/algorithms/hill_climbing.py
omnisearch/algorithms/iterative_deepening.py
omnisearch/algorithms/uniform_cost.py
omnisearch/data_structures/__init__.py
omnisearch/data_structures/priority_queue.py
omnisearch/data_structures/queue.py
omnisearch/data_structures/stack.py
omnisearch/interfaces/__init__.py
omnisearch/interfaces/state_space_problem.py
omnisearch/problems/__init__.py
omnisearch/problems/maze.py
omnisearch/problems/missionaries_and_cannibals.py
omnisearch/problems/n_queens.py
problems/__init__.py
problems/maze.py
problems/missionaries_and_cannibals.py
problems/n_queens.py
omnisearch-0.0.8.dist-info/LICENSE.txt
omnisearch-0.0.8.dist-info/METADATA
omnisearch-0.0.8.dist-info/WHEEL
omnisearch-0.0.8.dist-info/top_level.txt
omnisearch-0.0.8.dist-info/RECORD
